rest_framework_duration_iso_field/__init__.py
rest_framework_duration_iso_field-0.0.2.dist-info/LICENSE
rest_framework_duration_iso_field-0.0.2.dist-info/METADATA
rest_framework_duration_iso_field-0.0.2.dist-info/WHEEL
rest_framework_duration_iso_field-0.0.2.dist-info/top_level.txt
rest_framework_duration_iso_field-0.0.2.dist-info/RECORD
